reqtry/__init__.py
reqtry/reqtry.py
reqtry-0.0.2.dist-info/LICENSE
reqtry-0.0.2.dist-info/METADATA
reqtry-0.0.2.dist-info/WHEEL
reqtry-0.0.2.dist-info/top_level.txt
reqtry-0.0.2.dist-info/RECORD
