Metadata-Version: 2.1
Name: reqtry
Version: 0.0.2
Summary: A simple implementation of retries for request Python library
Home-page: https://github.com/marc0u/reqtry
Author: Marco Urriola
Author-email: marco.urriola@gmail.com
License: UNKNOWN
Platform: UNKNOWN
Classifier: Programming Language :: Python :: 3
Classifier: License :: OSI Approved :: MIT License
Classifier: Operating System :: OS Independent
Requires-Python: >=3.6
Requires-Dist: requests (==2.24.0)
